clear_s2s/APIHandler.py
clear_s2s/CLEAR/templates/BusinessSearchRequest.xml
clear_s2s/CLEAR/templates/CompanyQuickAnalysisFlagRequest.xml
clear_s2s/CLEAR/templates/EIDVPersonSearch.xml
clear_s2s/CLEAR/templates/PersonQuickAnalysisFlagRequest.xml
clear_s2s/CLEAR/templates/PersonSearchRequest.xml
clear_s2s/CLEAR/templates/WebAndSocialMediaSearchRequest.xml
clear_s2s/exceptions.py
clear_s2s/ThomsonReuters.py
clear_s2s-0.1.7.dist-info/WHEEL
clear_s2s-0.1.7.dist-info/METADATA
clear_s2s-0.1.7.dist-info/RECORD
