Metadata-Version: 2.1
Name: clear-s2s
Version: 0.1.7
Summary: 
License: BSD
Author: Your Name
Author-email: you@example.com
Requires-Python: >=3.6,<4.0
Classifier: License :: Other/Proprietary License
Classifier: Programming Language :: Python :: 3
Classifier: Programming Language :: Python :: 3.6
Classifier: Programming Language :: Python :: 3.7
Classifier: Programming Language :: Python :: 3.8
Classifier: Programming Language :: Python :: 3.9
Requires-Dist: Jinja2 (>=3.0.2,<4.0.0)
Requires-Dist: requests-pkcs12 (>=1.13,<2.0)
Requires-Dist: xmltodict (>=0.12.0,<0.13.0)
